pyramids_categories/adjective(er_ending).ctg
pyramids_categories/adjective(est_ending).ctg
pyramids_categories/adjective.ctg
"pyramids_categories/adverb(contrastive,direct).ctg"
pyramids_categories/adverb(degree).ctg
pyramids_categories/adverb(direct).ctg
"pyramids_categories/adverb(direct,negative,time).ctg"
"pyramids_categories/adverb(direct,time).ctg"
pyramids_categories/adverb(recursive).ctg
pyramids_categories/insult.ctg
pyramids_categories/interjection.ctg
"pyramids_categories/name(female,first,person).ctg"
"pyramids_categories/name(first,male,person).ctg"
"pyramids_categories/name(last,person).ctg"
pyramids_categories/name(pet).ctg
"pyramids_categories/name(s_ending,time).ctg"
pyramids_categories/name(time).ctg
pyramids_categories/noun(cause).ctg
"pyramids_categories/noun(cause,s_ending).ctg"
pyramids_categories/noun(object).ctg
"pyramids_categories/noun(object,s_ending).ctg"
pyramids_categories/noun(place).ctg
"pyramids_categories/noun(place,s_ending).ctg"
pyramids_categories/noun(style).ctg
"pyramids_categories/noun(s_ending,time).ctg"
pyramids_categories/noun(time).ctg
"pyramids_categories/number(digit,ordinal,small).ctg"
"pyramids_categories/number(digit,ordinal,tens).ctg"
"pyramids_categories/number(digit,small).ctg"
"pyramids_categories/number(digit,tens).ctg"
"pyramids_categories/number(ordinal,size).ctg"
"pyramids_categories/number(ordinal,small).ctg"
"pyramids_categories/number(ordinal,teen).ctg"
"pyramids_categories/number(ordinal,tens).ctg"
pyramids_categories/number(size).ctg
pyramids_categories/number(small).ctg
pyramids_categories/number(teen).ctg
pyramids_categories/number(tens).ctg
pyramids_categories/verb(ed_ending).ctg
pyramids_categories/verb(en_ending).ctg
pyramids_categories/verb(ing_ending).ctg
pyramids_categories/verb(s_ending).ctg
pyramids_categories/verb.ctg
pyramids_categories/__init__.py
pyramids_categories-1.0.0.dist-info/DESCRIPTION.rst
pyramids_categories-1.0.0.dist-info/METADATA
pyramids_categories-1.0.0.dist-info/metadata.json
pyramids_categories-1.0.0.dist-info/RECORD
pyramids_categories-1.0.0.dist-info/top_level.txt
pyramids_categories-1.0.0.dist-info/WHEEL
