Metadata-Version: 2.0
Name: pyramids-categories
Version: 1.0.0
Summary: Pyramids Categories: Pre-compiled category files for the Pyramids Parser
Home-page: https://github.com/hosford42/pyramids_categories
Author: Aaron Hosford
Author-email: hosford42@gmail.com
License: MIT
